photfdtd/__init__.py
photfdtd/arc.py
photfdtd/directional_coupler.py
photfdtd/mmi.py
photfdtd/ring.py
photfdtd/sbend.py
photfdtd/waveguide.py
photfdtd/ysplitter.py
photfdtd-0.0.5.dist-info/LICENSE
photfdtd-0.0.5.dist-info/WHEEL
photfdtd-0.0.5.dist-info/METADATA
photfdtd-0.0.5.dist-info/RECORD
