Metadata-Version: 2.1
Name: photfdtd
Version: 0.0.5
Summary: PyPhot FDTD package
Home-page: https://pypi.org/project/photfdtd/
License: MIT
Author: Chunyu Li
Author-email: cyli0212@gmail.com
Requires-Python: >=3.7,<4.0
Classifier: License :: OSI Approved :: MIT License
Classifier: Programming Language :: Python :: 3
Classifier: Programming Language :: Python :: 3.7
Classifier: Programming Language :: Python :: 3.8
Classifier: Programming Language :: Python :: 3.9
Classifier: Programming Language :: Python :: 3.10
Classifier: Programming Language :: Python :: 3.11
Requires-Dist: fdtd
Requires-Dist: matplotlib
Requires-Dist: numpy
Project-URL: Repository, https://github.com/phot-lab/photfdtd
